citio_trust_adrien
